getword/__init__.py
getword/adjectivelist.txt
getword/nounlist.txt
getword/random_sentence.py
getword/random_word.py
getword/verblist.txt
getword/words.txt
wonderwords/__init__.py
wonderwords/adjectivelist.txt
wonderwords/cmdline.py
wonderwords/cmdline_parser.py
wonderwords/nounlist.txt
wonderwords/random_sentence.py
wonderwords/random_word.py
wonderwords/test.py
wonderwords/verblist.txt
wonderwords/words.txt
wonderwords/assets/__init__.py
wonderwords/assets/adjectivelist.txt
wonderwords/assets/nounlist.txt
wonderwords/assets/verblist.txt
wonderwords-2.1.0.dist-info/LICENSE
wonderwords-2.1.0.dist-info/METADATA
wonderwords-2.1.0.dist-info/WHEEL
wonderwords-2.1.0.dist-info/entry_points.txt
wonderwords-2.1.0.dist-info/top_level.txt
wonderwords-2.1.0.dist-info/RECORD
