Metadata-Version: 2.1
Name: wonderwords
Version: 2.1.0
Summary: A python package for random words and sentences in the english language
Home-page: https://github.com/mrmaxguns/wonderwordsmodule
Author: Maxim Rebguns
Author-email: mrmaxguns@gmail.com
License: UNKNOWN
Platform: UNKNOWN
Classifier: Programming Language :: Python :: 3
Classifier: License :: OSI Approved :: MIT License
Classifier: Operating System :: OS Independent
Requires-Python: >=3.6
Requires-Dist: rich (==6.1.1)
Requires-Dist: importlib-resources (==3.0.0) ; python_version < "3.7"
